fastapi_and_babel/__init__.py
fastapi_and_babel/exceptions.py
fastapi_and_babel/middleware.py
fastapi_and_babel/translator.py
fastapi_and_babel-0.0.4.dist-info/LICENSE
fastapi_and_babel-0.0.4.dist-info/METADATA
fastapi_and_babel-0.0.4.dist-info/WHEEL
fastapi_and_babel-0.0.4.dist-info/top_level.txt
fastapi_and_babel-0.0.4.dist-info/RECORD
